SoraDBlite/SoraDBlite.py
SoraDBlite/__init__.py
SoraDefaultDB/SoraDefaultDB.py
SoraDefaultDB/__init__.py
SoraDBlite-2.0.21.dist-info/LICENSE
SoraDBlite-2.0.21.dist-info/METADATA
SoraDBlite-2.0.21.dist-info/WHEEL
SoraDBlite-2.0.21.dist-info/top_level.txt
SoraDBlite-2.0.21.dist-info/RECORD
