Metadata-Version: 2.1
Name: SoraDBlite
Version: 2.0.21
Summary: SoraDBlite is a Python class designed to simplify interactions with MongoDB databases, the operation of SoraDBlite is similar to the pymongo. It is also a lite version of pymongo.Added Sora AI integration for error detection and solution.
Home-page: https://amalnath.netlify.app/
Author: Amal Nath H
Author-email: amalnath0600@gmail.com
License: GNU GENERAL PUBLIC LICENSE
Project-URL: Documentation, https://soradblite-docs.netlify.app/
Project-URL: source, https://github.com/MrTG-CodeBot/SoraDBlite
Platform: UNKNOWN
Requires-Python: >=3.8.0
License-File: LICENSE
Requires-Dist: pymongo
Requires-Dist: google-generativeai
Requires-Dist: requests
